airless/google/cloud/bigquery/__init__.py
airless/google/cloud/bigquery/hook/__init__.py
airless/google/cloud/bigquery/hook/bigquery.py
airless/google/cloud/bigquery/operator/__init__.py
airless/google/cloud/bigquery/operator/bigquery.py
airless_google_cloud_bigquery-0.3.2.dist-info/METADATA
airless_google_cloud_bigquery-0.3.2.dist-info/WHEEL
airless_google_cloud_bigquery-0.3.2.dist-info/top_level.txt
airless_google_cloud_bigquery-0.3.2.dist-info/RECORD
