Metadata-Version: 2.4
Name: airless-google-cloud-bigquery
Version: 0.3.2
Summary: Airless package to works with google cloud bigquery
License: MIT License
Project-URL: Homepage, https://github.com/astercapital/airless
Project-URL: Bug Tracker, https://github.com/astercapital/airless/issues
Requires-Python: >=3.9
Requires-Dist: unidecode==1.3.4
Requires-Dist: google-cloud-bigquery<4.0.0,>=3.25.0
Requires-Dist: airless-google-cloud-core>=0.1.0
Requires-Dist: airless-google-cloud-storage>=0.1.0
